cafex/__init__.py
cafex/cafex.py
cafex-1.0.0.dist-info/METADATA
cafex-1.0.0.dist-info/WHEEL
cafex-1.0.0.dist-info/top_level.txt
cafex-1.0.0.dist-info/RECORD
