Metadata-Version: 2.4
Name: cafex
Version: 1.0.0
Summary: Complete cafex package
Author-email: QA Automation Team <qa_automation@gmail.com>
Project-URL: Homepage, https://example.com
Project-URL: Documentation, https://readthedocs.org
Project-URL: Repository, https://github.com/me/spam.git
Project-URL: Issues, https://github.com/me/spam/issues
Project-URL: Changelog, https://github.com/me/spam/blob/master/CHANGELOG.md
Keywords: ui,appium,selenium,pytest,automation,db,db testing,api,api testing
Classifier: Programming Language :: Python :: 3
Classifier: Operating System :: OS Independent
Requires-Python: >=3.12
Requires-Dist: cafex-core>=1.0.0
Requires-Dist: cafex-api>=1.0.0
Requires-Dist: cafex-db>=1.0.0
Requires-Dist: cafex-ui>=1.0.0
Requires-Dist: cafex-desktop>=1.0.0
